{
  "KillAura Enabled": true,
  "Disabler Enabled": true,
  "NoSlowdown Enabled": true,
  "LongJump Enabled": false,
  "TargetHUD Enabled": true,
  "Speed Enabled": false,
  "Velocity Enabled": true,
  "Inventory Move Enabled": true,
  "BoatFly Enabled": false,
  "NoScoreboard Enabled": true,
  "ChestStealer Enabled": false,
  "Fly Enabled": false,
  "InvManager Enabled": true,
  "NameTags Enabled": true,
  "BedFucker Enabled": false,
  "ChestESP Enabled": true,
  "Redesky Enabled": true,
  "ItemESP Enabled": false,
  "ClickGui Enabled": false,
  "AntiVoid Enabled": false,
  "Scaffold Enabled": false,
  "FastEat Enabled": false,
  "NoFall Enabled": false,
  "Phase Enabled": false,
  "Strafe Enabled": false,
  "Sprint Enabled": true,
  "Blink Enabled": false,
  "ESP Enabled": true,
  "SprintAllDirections": false,
  "KillAuraMinCPS": 20.0,
  "KillAuraMaxCPS": 20.0,
  "KillAuraRange": 6,
  "KillAuraRotations": true,
  "KillAuraStop": false,
  "KillAuraAutoBlock": true,
  "KillAuraAutoBlockMode": "Redesky2",
  "KillAuraRandomRotations": false,
  "KillAuraMinRotationSpeed": 29.0,
  "KillAuraMaxRotationSpeed": 116.0,
  "KillAuraTeams": true,
  "KillAuraMoveFix": true,
  "VMode": "Normal",
  "SpeedMode": "Redesky",
  "FlyMode": "Vanilla",
  "CGMode": "Drip",
  "LJMode": "Redesky",
  "LJAwaitDamage": false,
  "CSDelay": 56.0,
  "IMDelay": 57.0,
  "IMOpenInv": true,
  "ScaffoldSprint": false,
  "ScaffoldPlaceMethod": "Normal",
  "ScaffoldRotateWhenPlacing": false,
  "ScaffoldCubecraft": false,
  "ScaffoldRedesky": true,
  "TargetStrafe": false
}
